LICENSE
MANIFEST.in
Makefile
README
setup.cfg
setup.py
twibuilder
test/__init__.py
test/__init__.pyc
test/test_cache.py
test/test_compile.py
test/__pycache__/test_cache.cpython-27-PYTEST.pyc
test/__pycache__/test_compile.cpython-27-PYTEST.pyc
tiddlywebplugins/__init__.py
tiddlywebplugins/ibuilder.py
tiddlywebplugins.ibuilder.egg-info/PKG-INFO
tiddlywebplugins.ibuilder.egg-info/SOURCES.txt
tiddlywebplugins.ibuilder.egg-info/dependency_links.txt
tiddlywebplugins.ibuilder.egg-info/namespace_packages.txt
tiddlywebplugins.ibuilder.egg-info/not-zip-safe
tiddlywebplugins.ibuilder.egg-info/requires.txt
tiddlywebplugins.ibuilder.egg-info/top_level.txt