Metadata-Version: 1.0
Name: tiddlywebplugins.ibuilder
Version: 0.1.4
Summary: Build TiddlyWeb instance packages
Home-page: http://pypi.python.org/pypi/tiddlywebplugins.ibuilder
Author: Chris Dent
Author-email: cdent@peermore.com
License: UNKNOWN
Platform: Posix; MacOS X; Windows
